<?xml version="1.0" encoding="UTF-8"?>
<Verificacion>
  <VerificacionID>1</VerificacionID>
  <VerificacionFolio>123456</VerificacionFolio>
  <VerificacionFecha>2024-02-01</VerificacionFecha>
  <VerificacionDictamen>Aprobado</VerificacionDictamen>
  <VerificacionTecnico>IDK No se que sea esto</VerificacionTecnico>
  <VerificacionHoraEntrada>10:32:15</VerificacionHoraEntrada>
  <VerificacionHoraSalida>11:32:15</VerificacionHoraSalida>
  <VerificacionFolioPrueba>23456</VerificacionFolioPrueba>
  <VerificacionVigencia>0000-00-00</VerificacionVigencia>
  <VerificacionSemestre>2</VerificacionSemestre>
  <VerificacionTipo>Idk</VerificacionTipo>
  <VerificacionLinea>3</VerificacionLinea>
  <VerificacionNiv>34674742</VerificacionNiv>
  <VerificacionMotivo>No se bro esta raro esto</VerificacionMotivo>
  <CentroRazonSocial>Centro Veri JOSEJU SA. de CV.</CentroRazonSocial>
  <CentroNombre>Centro Veri JOSEJU PRO MAX</CentroNombre>
  <CentroTelefono>46123456</CentroTelefono>
  <TarjetaFolio>123456</TarjetaFolio>
  <TarjetaVigencia>2025</TarjetaVigencia>
  <TarjetaOperacion>Nosabo</TarjetaOperacion>
  <TarjetaFolio_2>123456</TarjetaFolio_2>
  <TarjetaFechaExp>2024-04-09</TarjetaFechaExp>
  <TarjetaOficinaExpedidora>2</TarjetaOficinaExpedidora>
  <TarjetaOE_Movimiento>No se que chuchas estpy ahciendo </TarjetaOE_Movimiento>
  <TarjetaNumConstancia>666</TarjetaNumConstancia>
  <TarjetaCalle>Alamo</TarjetaCalle>
  <TarjetaNumero>9</TarjetaNumero>
  <TarjetaColonia>Noria de Sopeña</TarjetaColonia>
  <TarjetaMunicipio>Leon </TarjetaMunicipio>
  <TarjetaLocalidad>Leon </TarjetaLocalidad>
  <VehiculoNoSerie>34567834</VehiculoNoSerie>
  <VehiculoPlaca>GKU890767</VehiculoPlaca>
  <VehiculoTServicio>Particular</VehiculoTServicio>
  <VehiculoMarca>Chirey</VehiculoMarca>
  <VehiculoModelo>2023</VehiculoModelo>
  <VehiculoOrigen>China</VehiculoOrigen>
  <VehiculoColor>Gris</VehiculoColor>
  <VehiculoCilindraje>6</VehiculoCilindraje>
  <VehiculoCapacidad>127</VehiculoCapacidad>
  <VehiculoClase>2</VehiculoClase>
  <VehiculoTipo>6</VehiculoTipo>
  <VehiculoUso>56</VehiculoUso>
  <VehiculoPuerta>4</VehiculoPuerta>
  <VehiculoAsiento>5</VehiculoAsiento>
  <VehiculoCombustible>1</VehiculoCombustible>
  <VehiculoTransmision>Automatico</VehiculoTransmision>
  <VehiculoNoMotor>23123213</VehiculoNoMotor>
  <PropietarioNombre>Luis Julian</PropietarioNombre>
  <PropietarioApellido>Olalde</PropietarioApellido>
  <PropietarioRFC>OLAL003</PropietarioRFC>
  <PropietarioSexo>Masculino</PropietarioSexo>
  <PropietarioEdoProcedencia>Guanajuato</PropietarioEdoProcedencia>
  <CentroDireccionCalle>Francisco I. Madero</CentroDireccionCalle>
  <CentroDireccionNumero>260</CentroDireccionNumero>
  <CentroDireccionColonia>Niños Heroes</CentroDireccionColonia>
  <CentroDireccionMunicipio>Santiago de Queretaro</CentroDireccionMunicipio>
  <CentroDireccionLocalidad>Quereataro</CentroDireccionLocalidad>
</Verificacion>
